browsinator/__init__.py
browsinator-0.1.2.dist-info/METADATA
browsinator-0.1.2.dist-info/WHEEL
browsinator-0.1.2.dist-info/top_level.txt
browsinator-0.1.2.dist-info/RECORD
