Metadata-Version: 2.1
Name: browsinator
Version: 0.1.2
Summary: A Python library for programmatically controlling and interacting with a web browser using the Chrome DevTools Protocol
Home-page: https://github.com/slava-vishnyakov/browsinator
Author: Slava Vishnyakov
Author-email: bomboze@gmail.com
Classifier: Development Status :: 3 - Alpha
Classifier: Intended Audience :: Developers
Classifier: License :: OSI Approved :: MIT License
Classifier: Operating System :: OS Independent
Classifier: Programming Language :: Python :: 3
Classifier: Programming Language :: Python :: 3.6
Classifier: Programming Language :: Python :: 3.7
Classifier: Programming Language :: Python :: 3.8
Classifier: Programming Language :: Python :: 3.9
Requires-Python: >=3.6
Requires-Dist: requests
Requires-Dist: websocket-client
